allanms/__init__.py
allanms/courses.py
allanms/utils.py
allanms-0.1.1.dist-info/METADATA
allanms-0.1.1.dist-info/WHEEL
allanms-0.1.1.dist-info/top_level.txt
allanms-0.1.1.dist-info/RECORD
