Metadata-Version: 2.1
Name: allanms
Version: 0.1.1
Summary: Una biblioteca para consultar cursos de la plataforma hack4u
Home-page: https://hack4u.io
Author: Allan Murillo
